daedaluspy/__init__.py
daedaluspy/__main__.py
daedaluspy/cli.py
daedaluspy/data_lib/__init__.py
daedaluspy/data_lib/data/__init__.py
daedaluspy/data_lib/data/base_template.py
daedaluspy/data_lib/data/cloud_aws/__init__.py
daedaluspy/data_lib/data/cloud_aws/template/__init__.py
daedaluspy/data_lib/data/cloud_aws/template/container_files/__init__.py
daedaluspy/data_lib/data/cloud_aws/template/container_files/entity_template.py
daedaluspy/data_lib/data/cloud_azure/__init__.py
daedaluspy/data_lib/data/cloud_azure/template/__init__.py
daedaluspy/data_lib/data/cloud_azure/template/container_files/__init__.py
daedaluspy/data_lib/data/cloud_azure/template/container_files/entity_template.py
daedaluspy/data_lib/data/cloud_google/__init__.py
daedaluspy/data_lib/data/cloud_google/template/__init__.py
daedaluspy/data_lib/data/cloud_google/template/container_files/__init__.py
daedaluspy/data_lib/data/cloud_google/template/container_files/entity_template.py
daedaluspy/data_lib/generator/__init__.py
daedaluspy/data_lib/generator/data_entity_oop.py
daedaluspy/data_lib/generator/library_generator.py
daedaluspy/data_lib/generator/service_generator_oop.py
daedaluspy/data_lib/generator/setup_file.py
daedaluspy/data_lib/generator/templates/__init__.py
daedaluspy/data_lib/generator/templates/config_templates.py
daedaluspy/data_lib/generator/templates/data_quality_templates.py
daedaluspy/data_lib/generator/templates/logger_templates.py
daedaluspy/data_lib/generator/templates/setup_template.py
daedaluspy/data_lib/services/__init__.py
daedaluspy/data_lib/services/generator/corporate_service_generator.py
daedaluspy/data_lib/services/template/__init__.py
daedaluspy/data_lib/services/template/apis/__init__.py
daedaluspy/data_lib/services/template/apis/auth_template.py
daedaluspy/data_lib/services/template/apis/models_template.py
daedaluspy/data_lib/services/template/apis/service_template.py
daedaluspy/data_lib/services/template/database/__init__.py
daedaluspy-1.0.3.dist-info/licenses/LICENSE
daedaluspy-1.0.3.dist-info/METADATA
daedaluspy-1.0.3.dist-info/WHEEL
daedaluspy-1.0.3.dist-info/entry_points.txt
daedaluspy-1.0.3.dist-info/top_level.txt
daedaluspy-1.0.3.dist-info/RECORD
