Metadata-Version: 2.4
Name: daedaluspy
Version: 1.0.3
Summary: Code generation toolkit for data engineering
Home-page: https://github.com/Golden-Valley-Consulting/DaedalusPy
Author: Golden Valley Consulting LTDA
Author-email: Golden Valley Consulting LTDA <contato@goldenvalleyc.com>
License-Expression: MIT
Project-URL: Homepage, https://github.com/Golden-Valley-Consulting/daedaluspy
Project-URL: Documentation, https://daedaluspy.readthedocs.io
Project-URL: Repository, https://github.com/Golden-Valley-Consulting/daedaluspy
Project-URL: Bug Tracker, https://github.com/Golden-Valley-Consulting/daedaluspy/issues
Keywords: code-generation,data-engineering,python,cli
Classifier: Development Status :: 4 - Beta
Classifier: Intended Audience :: Developers
Classifier: Operating System :: OS Independent
Classifier: Programming Language :: Python :: 3
Classifier: Programming Language :: Python :: 3.7
Classifier: Programming Language :: Python :: 3.8
Classifier: Programming Language :: Python :: 3.9
Classifier: Programming Language :: Python :: 3.10
Classifier: Programming Language :: Python :: 3.11
Classifier: Programming Language :: Python :: 3.12
Classifier: Programming Language :: Python :: 3.13
Classifier: Topic :: Software Development :: Code Generators
Classifier: Topic :: Software Development :: Libraries :: Python Modules
Requires-Python: >=3.7
License-File: LICENSE
Provides-Extra: dev
Requires-Dist: pytest>=6.0; extra == "dev"
Requires-Dist: black; extra == "dev"
Requires-Dist: flake8; extra == "dev"
Requires-Dist: mypy; extra == "dev"
Dynamic: author
Dynamic: home-page
Dynamic: license-file
Dynamic: requires-python
